dRFEtools/__init__.py
dRFEtools/_dev_scoring.py
dRFEtools/_lowess_redundant.py
dRFEtools/_random_forest.py
dRFEtools/_rank_function.py
dRFEtools/dRFEtools.py
drfetools-0.3.5.dist-info/LICENSE
drfetools-0.3.5.dist-info/METADATA
drfetools-0.3.5.dist-info/WHEEL
drfetools-0.3.5.dist-info/RECORD
