Metadata-Version: 2.1
Name: dRFEtools
Version: 0.3.5
Summary: A package for preforming dynamic recursive feature elimination with sklearn.
Home-page: https://github.com/LieberInstitute/dRFEtools.git
License: GPL-3.0-only
Keywords: recursive feature elimination,sklearn,feature ranking
Author: Kynon JM Benjamin
Author-email: kj.benjamin90@gmail.com
Maintainer: Kynon JM Benjamin
Maintainer-email: kj.benjamin90@gmail.com
Requires-Python: >=3.10,<4.0
Classifier: License :: OSI Approved :: GNU General Public License v3 (GPLv3)
Classifier: Programming Language :: Python :: 3
Classifier: Programming Language :: Python :: 3.10
Classifier: Programming Language :: Python :: 3.11
Classifier: Programming Language :: Python :: 3.12
Requires-Dist: matplotlib (>=3.7,<4.0)
Requires-Dist: numpy (>=2.0,<3.0)
Requires-Dist: pandas (>=2.0,<3.0)
Requires-Dist: plotnine (>=0.13,<0.14)
Requires-Dist: scikit-learn (>=1.2,<2.0)
Requires-Dist: scipy (>=1.14,<2.0)
Requires-Dist: statsmodels (>=0.14,<0.15)
Project-URL: Repository, https://github.com/LieberInstitute/dRFEtools.git
